Workbook

Sheet Cover
B3: BUDGET BY PAYCHECK
B6: Bi-Weekly Budget, Savings & Debt Tracker
B8: WHAT'S INSIDE · 14 TABS
B9: START HERE — Instructions — set up in minutes
B10: PLAN — Paycheck · Budget · 50/30/20
B11: TRACK — Bills · Subscriptions · Paycheck Log
B12: GROW — Savings Goals · Sinking Funds
B13: CRUSH DEBT — Debt Payoff with payoff progress
B14: NET WORTH — Net Worth · Annual Overview
B15: SEE IT ALL — Dashboard — every number, live
B17: Only the shaded cells need you — everything else is automatic
B18: ♡ Thank you for your purchase · made with care

Sheet How-to
A1: Step | B1: What to do
A2: 1 | B2: Make your own copy first (File ▸ Make a copy / Save As) so the original stays clean.
A3: 2 | B3: Paycheck tab: enter your gross pay and each deduction. Take-home pay calculates itself.
A4: 3 | B4: Budget tab: set a Budgeted amount per category. Aim to keep 'Left to allocate' at 0.
A5: 4 | B5: Bills & Subscriptions: list what you owe each month and tick off bills as you pay them.
A6: 5 | B6: Paycheck Log: each payday, type what you Spent. Saved and Cumulative saved fill in for you.
A7: 6 | B7: Savings Goals & Sinking Funds: set targets and dates — your monthly contribution is calculated.
A8: 7 | B8: Debt Payoff & Net Worth: enter balances and watch '% paid' and your net worth update.
A9: 8 | B9: Dashboard & Annual Overview: open any time for your whole financial picture and charts.
A10: ★ | B10: Tip: only shaded input cells need you. Hide any tabs you don't use — totals still work.

Sheet Paycheck
A1: Item | B1: Per paycheck | C1: Per year (×26)
A2: Gross pay | B2: 2200 | C2: =B2*26
A3: Federal tax | B3: 264 | C3: =B3*26
A4: State tax | B4: 88 | C4: =B4*26
A5: FICA (Social Security + Medicare) | B5: 168 | C5: =B5*26
A6: Health insurance | B6: 95 | C6: =B6*26
A7: 401(k) retirement | B7: 132 | C7: =B7*26
A8: Total deductions | B8: =SUM(B3:B7) | C8: =B8*26
A9: Take-home pay (net) | B9: =B2-B8 | C9: =B9*26

Sheet Budget
A1: Category | B1: Budgeted | C1: % of take-home
A2: Rent / housing | B2: 600 | C2: =IF($B$13=0,0,B2/$B$13)
A3: Utilities | B3: 90 | C3: =IF($B$13=0,0,B3/$B$13)
A4: Groceries | B4: 220 | C4: =IF($B$13=0,0,B4/$B$13)
A5: Transportation / gas | B5: 100 | C5: =IF($B$13=0,0,B5/$B$13)
A6: Phone + internet | B6: 60 | C6: =IF($B$13=0,0,B6/$B$13)
A7: Subscriptions | B7: 30 | C7: =IF($B$13=0,0,B7/$B$13)
A8: Debt payment | B8: 100 | C8: =IF($B$13=0,0,B8/$B$13)
A9: Savings | B9: 150 | C9: =IF($B$13=0,0,B9/$B$13)
A10: Fun / dining out | B10: 60 | C10: =IF($B$13=0,0,B10/$B$13)
A11: Miscellaneous | B11: 43 | C11: =IF($B$13=0,0,B11/$B$13)
A12: Total budgeted | B12: =SUM(B2:B11) | C12: =IF($B$13=0,0,B12/$B$13)
A13: Take-home pay (net) | B13: =Paycheck!B9
A14: Left to allocate | B14: =B13-B12

Sheet 50-30-20
A1: Bucket | B1: Target % | C1: Target $ / paycheck | D1: Your plan $ | E1: Difference
A2: Needs (housing, food…) | B2: 0.5 | C2: =Paycheck!$B$9*B2 | D2: =SUM(Budget!B2:B6) | E2: =D2-C2
A3: Wants (fun, subs…) | B3: 0.3 | C3: =Paycheck!$B$9*B3 | D3: =Budget!B7+Budget!B10+Budget!B11 | E3: =D3-C3
A4: Savings & debt | B4: 0.2 | C4: =Paycheck!$B$9*B4 | D4: =Budget!B8+Budget!B9 | E4: =D4-C4
A5: Total | B5: =SUM(B2:B4) | C5: =SUM(C2:C4) | D5: =SUM(D2:D4) | E5: =D5-C5

Sheet Bills
A1: Bill | B1: Due day | C1: Amount | D1: Autopay | E1: Status | F1: Category
A2: Rent / mortgage | B2: 1 | C2: 1200 | D2: No | E2: Unpaid | F2: Housing
A3: Electric | B3: 5 | C3: 90 | D3: Yes | E3: Paid | F3: Utilities
A4: Internet | B4: 10 | C4: 60 | D4: Yes | E4: Paid | F4: Utilities
A5: Phone | B5: 15 | C5: 45 | D5: Yes | E5: Unpaid | F5: Utilities
A6: Car insurance | B6: 20 | C6: 110 | D6: No | E6: Unpaid | F6: Insurance
A7: Water | B7: 22 | C7: 40 | D7: No | E7: Unpaid | F7: Utilities
A8: Gym | B8: 25 | C8: 30 | D8: Yes | E8: Paid | F8: Health
A9: Credit card | B9: 28 | C9: 150 | D9: No | E9: Unpaid | F9: Debt
A10: Total | C10: =SUM(C2:C9)

Sheet Subscriptions
A1: Subscription | B1: Monthly cost | C1: Annual cost | D1: Category
A2: Netflix | B2: 15.49 | C2: =B2*12 | D2: Streaming
A3: Spotify | B3: 11.99 | C3: =B3*12 | D3: Music
A4: Amazon Prime | B4: 14.99 | C4: =B4*12 | D4: Shopping
A5: iCloud storage | B5: 2.99 | C5: =B5*12 | D5: Software
A6: Disney+ | B6: 13.99 | C6: =B6*12 | D6: Streaming
A7: Adobe | B7: 20.99 | C7: =B7*12 | D7: Software
A8: YouTube Premium | B8: 13.99 | C8: =B8*12 | D8: Streaming
A9: Total | B9: =SUM(B2:B8) | C9: =SUM(C2:C8)

Sheet Log
A1: # | B1: Pay date | C1: Net pay | D1: Spent | E1: Saved | F1: Cumulative saved
A2: 1 | B2: =DATE(2026,1,2)+14*(2-2) | C2: =Paycheck!$B$9 | D2: 1303 | E2: =C2-D2 | F2: =SUM($E$2:E2)
A3: 2 | B3: =DATE(2026,1,2)+14*(3-2) | C3: =Paycheck!$B$9 | D3: 1303 | E3: =C3-D3 | F3: =SUM($E$2:E3)
A4: 3 | B4: =DATE(2026,1,2)+14*(4-2) | C4: =Paycheck!$B$9 | D4: 1303 | E4: =C4-D4 | F4: =SUM($E$2:E4)
A5: 4 | B5: =DATE(2026,1,2)+14*(5-2) | C5: =Paycheck!$B$9 | D5: 1303 | E5: =C5-D5 | F5: =SUM($E$2:E5)
A6: 5 | B6: =DATE(2026,1,2)+14*(6-2) | C6: =Paycheck!$B$9 | D6: 1303 | E6: =C6-D6 | F6: =SUM($E$2:E6)
A7: 6 | B7: =DATE(2026,1,2)+14*(7-2) | C7: =Paycheck!$B$9 | D7: 1303 | E7: =C7-D7 | F7: =SUM($E$2:E7)
A8: 7 | B8: =DATE(2026,1,2)+14*(8-2) | C8: =Paycheck!$B$9 | D8: 1303 | E8: =C8-D8 | F8: =SUM($E$2:E8)
A9: 8 | B9: =DATE(2026,1,2)+14*(9-2) | C9: =Paycheck!$B$9 | D9: 1303 | E9: =C9-D9 | F9: =SUM($E$2:E9)
A10: 9 | B10: =DATE(2026,1,2)+14*(10-2) | C10: =Paycheck!$B$9 | D10: 1303 | E10: =C10-D10 | F10: =SUM($E$2:E10)
A11: 10 | B11: =DATE(2026,1,2)+14*(11-2) | C11: =Paycheck!$B$9 | D11: 1303 | E11: =C11-D11 | F11: =SUM($E$2:E11)
A12: 11 | B12: =DATE(2026,1,2)+14*(12-2) | C12: =Paycheck!$B$9 | D12: 1303 | E12: =C12-D12 | F12: =SUM($E$2:E12)
A13: 12 | B13: =DATE(2026,1,2)+14*(13-2) | C13: =Paycheck!$B$9 | D13: 1303 | E13: =C13-D13 | F13: =SUM($E$2:E13)
A14: 13 | B14: =DATE(2026,1,2)+14*(14-2) | C14: =Paycheck!$B$9 | D14: 1303 | E14: =C14-D14 | F14: =SUM($E$2:E14)
A15: 14 | B15: =DATE(2026,1,2)+14*(15-2) | C15: =Paycheck!$B$9 | D15: 1303 | E15: =C15-D15 | F15: =SUM($E$2:E15)
A16: 15 | B16: =DATE(2026,1,2)+14*(16-2) | C16: =Paycheck!$B$9 | D16: 1303 | E16: =C16-D16 | F16: =SUM($E$2:E16)
A17: 16 | B17: =DATE(2026,1,2)+14*(17-2) | C17: =Paycheck!$B$9 | D17: 1303 | E17: =C17-D17 | F17: =SUM($E$2:E17)
A18: 17 | B18: =DATE(2026,1,2)+14*(18-2) | C18: =Paycheck!$B$9 | D18: 1303 | E18: =C18-D18 | F18: =SUM($E$2:E18)
A19: 18 | B19: =DATE(2026,1,2)+14*(19-2) | C19: =Paycheck!$B$9 | D19: 1303 | E19: =C19-D19 | F19: =SUM($E$2:E19)
A20: 19 | B20: =DATE(2026,1,2)+14*(20-2) | C20: =Paycheck!$B$9 | D20: 1303 | E20: =C20-D20 | F20: =SUM($E$2:E20)
A21: 20 | B21: =DATE(2026,1,2)+14*(21-2) | C21: =Paycheck!$B$9 | D21: 1303 | E21: =C21-D21 | F21: =SUM($E$2:E21)
A22: 21 | B22: =DATE(2026,1,2)+14*(22-2) | C22: =Paycheck!$B$9 | D22: 1303 | E22: =C22-D22 | F22: =SUM($E$2:E22)
A23: 22 | B23: =DATE(2026,1,2)+14*(23-2) | C23: =Paycheck!$B$9 | D23: 1303 | E23: =C23-D23 | F23: =SUM($E$2:E23)
A24: 23 | B24: =DATE(2026,1,2)+14*(24-2) | C24: =Paycheck!$B$9 | D24: 1303 | E24: =C24-D24 | F24: =SUM($E$2:E24)
A25: 24 | B25: =DATE(2026,1,2)+14*(25-2) | C25: =Paycheck!$B$9 | D25: 1303 | E25: =C25-D25 | F25: =SUM($E$2:E25)
A26: 25 | B26: =DATE(2026,1,2)+14*(26-2) | C26: =Paycheck!$B$9 | D26: 1303 | E26: =C26-D26 | F26: =SUM($E$2:E26)
A27: 26 | B27: =DATE(2026,1,2)+14*(27-2) | C27: =Paycheck!$B$9 | D27: 1303 | E27: =C27-D27 | F27: =SUM($E$2:E27)

Sheet Savings Goals
A1: Goal | B1: Target | C1: Saved | D1: Remaining | E1: % Complete | F1: Target date
A2: Emergency fund | B2: 5000 | C2: 1500 | D2: =MAX(B2-C2,0) | E2: =IF(B2=0,0,C2/B2) | F2: =DATE(2026,12,31)
A3: Vacation | B3: 2500 | C3: 800 | D3: =MAX(B3-C3,0) | E3: =IF(B3=0,0,C3/B3) | F3: =DATE(2026,8,15)
A4: New car fund | B4: 8000 | C4: 2200 | D4: =MAX(B4-C4,0) | E4: =IF(B4=0,0,C4/B4) | F4: =DATE(2027,6,1)
A5: Holiday gifts | B5: 1200 | C5: 300 | D5: =MAX(B5-C5,0) | E5: =IF(B5=0,0,C5/B5) | F5: =DATE(2026,12,1)
A6: Home down payment | B6: 20000 | C6: 4500 | D6: =MAX(B6-C6,0) | E6: =IF(B6=0,0,C6/B6) | F6: =DATE(2028,1,1)
A7: Total | B7: =SUM(B2:B6) | C7: =SUM(C2:C6) | D7: =SUM(D2:D6) | E7: =IF(B7=0,0,C7/B7)

Sheet Sinking Funds
A1: Fund | B1: Target | C1: Saved | D1: Need by | E1: Months left | F1: Monthly set-aside | G1: Remaining
A2: Car maintenance | B2: 1200 | C2: 300 | D2: =DATE(2026,12,1) | E2: =MAX(DATEDIF(TODAY(),D2,"m"),1) | F2: =MAX(B2-C2,0)/E2 | G2: =MAX(B2-C2,0)
A3: Holidays / gifts | B3: 1000 | C3: 250 | D3: =DATE(2026,12,15) | E3: =MAX(DATEDIF(TODAY(),D3,"m"),1) | F3: =MAX(B3-C3,0)/E3 | G3: =MAX(B3-C3,0)
A4: Annual insurance | B4: 1400 | C4: 600 | D4: =DATE(2027,3,1) | E4: =MAX(DATEDIF(TODAY(),D4,"m"),1) | F4: =MAX(B4-C4,0)/E4 | G4: =MAX(B4-C4,0)
A5: Medical / dental | B5: 800 | C5: 200 | D5: =DATE(2026,11,1) | E5: =MAX(DATEDIF(TODAY(),D5,"m"),1) | F5: =MAX(B5-C5,0)/E5 | G5: =MAX(B5-C5,0)
A6: Home repairs | B6: 2000 | C6: 500 | D6: =DATE(2027,6,1) | E6: =MAX(DATEDIF(TODAY(),D6,"m"),1) | F6: =MAX(B6-C6,0)/E6 | G6: =MAX(B6-C6,0)
A7: Travel | B7: 1500 | C7: 400 | D7: =DATE(2026,9,1) | E7: =MAX(DATEDIF(TODAY(),D7,"m"),1) | F7: =MAX(B7-C7,0)/E7 | G7: =MAX(B7-C7,0)
A8: Total | B8: =SUM(B2:B7) | C8: =SUM(C2:C7) | F8: =SUM(F2:F7) | G8: =SUM(G2:G7)

Sheet Debt Payoff
A1: Debt | B1: Starting balance | C1: Current balance | D1: Paid off | E1: % paid | F1: APR | G1: Min payment
A2: Credit card | B2: 4200 | C2: 3100 | D2: =B2-C2 | E2: =IF(B2=0,0,D2/B2) | F2: 0.1999 | G2: 120
A3: Car loan | B3: 18000 | C3: 11500 | D3: =B3-C3 | E3: =IF(B3=0,0,D3/B3) | F3: 0.0549 | G3: 340
A4: Student loan | B4: 24000 | C4: 15800 | D4: =B4-C4 | E4: =IF(B4=0,0,D4/B4) | F4: 0.045 | G4: 210
A5: Personal loan | B5: 6000 | C5: 2400 | D5: =B5-C5 | E5: =IF(B5=0,0,D5/B5) | F5: 0.11 | G5: 180
A6: Total | B6: =SUM(B2:B5) | C6: =SUM(C2:C5) | D6: =SUM(D2:D5) | E6: =IF(B6=0,0,D6/B6) | G6: =SUM(G2:G5)

Sheet Net Worth
A1: Account | B1: Type | C1: Value
A2: Checking | B2: Asset | C2: 2500
A3: Savings | B3: Asset | C3: 9300
A4: Investments | B4: Asset | C4: 6000
A5: Retirement (401k/IRA) | B5: Asset | C5: 18000
A6: Car value | B6: Asset | C6: 12000
A7: Credit card | B7: Liability | C7: 3100
A8: Car loan | B8: Liability | C8: 11500
A9: Student loan | B9: Liability | C9: 15800
A10: Total assets | C10: =SUMIF($B$2:$B$9,"Asset",$C$2:$C$9)
A11: Total liabilities | C11: =SUMIF($B$2:$B$9,"Liability",$C$2:$C$9)
A12: NET WORTH | C12: =C10-C11

Sheet Annual Overview
A1: Metric | B1: Amount
A2: Annual gross income | B2: =Paycheck!B2*26
A3: Annual take-home (net) | B3: =Paycheck!B9*26
A4: Annual savings | B4: =SUM(Log!E2:E27)
A5: Annual subscriptions | B5: =SUM(Subscriptions!C2:C8)
A6: Annual bills | B6: =SUM(Bills!C2:C9)*12
A7: Total debt remaining | B7: ='Debt Payoff'!C6
A8: Total net worth | B8: ='Net Worth'!C12
A9: Savings rate | B9: =IF(B3=0,0,B4/B3)

Sheet Dashboard
C2: M O N E Y A T A G L A N C E
C4: Take-home / paycheck | E4: Avg monthly income | G4: Saved / year | I4: Savings rate
C5: =Paycheck!B9 | E5: =Paycheck!B9*26/12 | G5: =SUM(Log!E2:E27) | I5: =IF(SUM(Log!C2:C27)=0,0,SUM(Log!E2:E27)/SUM(Log!C2:C27))
C7: Total saved (goals) | E7: Goals progress | G7: Total debt left | I7: Debt paid off
C8: =SUM('Savings Goals'!C2:C6) | E8: =IF(SUM('Savings Goals'!B2:B6)=0,0,SUM('Savings Goals'!C2:C6)/SUM('Savings Goals'!B2:B6)) | G8: ='Debt Payoff'!C6 | I8: ='Debt Payoff'!D6
C10: Net worth | E10: Monthly bills | G10: Yearly subscriptions | I10: Sinking funds saved
C11: ='Net Worth'!C12 | E11: =SUM(Bills!C2:C9) | G11: =SUM(Subscriptions!C2:C8) | I11: =SUM('Sinking Funds'!C2:C7)
C13: B U D G E T B Y C A T E G O R Y
C28: S A V I N G S G R O W T H · 26 P A Y C H E C K S
C43: G O A L S · T A R G E T vs S A V E D
C58: 5 0 / 3 0 / 2 0 S P L I T
